zform/__init__.py
zform/constants.py
zform/form.py
zform/py.typed
zform/fields/__init__.py
zform/fields/base.py
zform/fields/boolean.py
zform/fields/dates.py
zform/fields/enum.py
zform/fields/files.py
zform/fields/flist.py
zform/fields/label.py
zform/fields/numbers.py
zform/fields/obj.py
zform/fields/select.py
zform/fields/string.py
zform/fields/widget.py
zform/fields/utils/__init__.py
zform/fields/utils/timezones.py
zform/params/__init__.py
zform/params/decorators.py
zform/params/field_infos.py
zform/params/resolver_gen.py
zform/params/resolvers.py
ellar_form-0.1.2.dist-info/WHEEL
ellar_form-0.1.2.dist-info/METADATA
ellar_form-0.1.2.dist-info/RECORD
